db2table.py
db2table-0.2.1.dist-info/DESCRIPTION.rst
db2table-0.2.1.dist-info/METADATA
db2table-0.2.1.dist-info/RECORD
db2table-0.2.1.dist-info/WHEEL
db2table-0.2.1.dist-info/entry_points.txt
db2table-0.2.1.dist-info/metadata.json
db2table-0.2.1.dist-info/top_level.txt
